config/photoslideshow_config.ini
photoslideshow/__init__.py
photoslideshow/photoslideshow.py
photoslideshow/common/__init__.py
photoslideshow/common/files_handler.py
photoslideshow/common/photo.py
photoslideshow/gui/__init__.py
photoslideshow/gui/app.py
photoslideshow/gui/photo_frame.py
photoslideshow/gui/window_about.py
photoslideshow/gui/window_config.py
photoslideshow/gui/window_fullscreen.py
resources/photoslideshow.png
resources/photoslideshow_ico.png
photo_slideshow-1.1.0.dist-info/LICENSE
photo_slideshow-1.1.0.dist-info/METADATA
photo_slideshow-1.1.0.dist-info/WHEEL
photo_slideshow-1.1.0.dist-info/entry_points.txt
photo_slideshow-1.1.0.dist-info/top_level.txt
photo_slideshow-1.1.0.dist-info/RECORD
