Metadata-Version: 2.1
Name: photo-slideshow
Version: 1.1.0
Summary: Simple tool to make a slideshow of your photos in selected directory and all the subdirectories.
Author-email: Mateusz Poślednik <matipos002@yahoo.com>
License: MIT
Project-URL: repository, https://github.com/matipos2/photo-slideshow
Project-URL: homepage, https://github.com/matipos2/photo-slideshow
Keywords: photo,slideshow,viewer,presentation
Classifier: Development Status :: 3 - Alpha
Classifier: License :: OSI Approved :: MIT License
Classifier: Programming Language :: Python :: 3
Classifier: Topic :: Multimedia :: Graphics :: Viewers
License-File: LICENSE
Requires-Dist: Pillow >=10.0
